fastjwt/__init__.py
fastjwt/_callback.py
fastjwt/_errors.py
fastjwt/config.py
fastjwt/core.py
fastjwt/dependencies.py
fastjwt/exceptions.py
fastjwt/fastjwt.py
fastjwt/models.py
fastjwt/token.py
fastjwt/types.py
fastjwt/utils.py
fastjwt-0.4.1.dist-info/LICENSE
fastjwt-0.4.1.dist-info/METADATA
fastjwt-0.4.1.dist-info/WHEEL
fastjwt-0.4.1.dist-info/RECORD
