Metadata-Version: 2.1
Name: fastjwt
Version: 0.4.1
Summary: FastAPI Plugin for reusable JWT Authentication Management
Home-page: https://ocarinow.github.io/fastjwt/
License: MIT
Keywords: fastapi,jwt,JSON-Web-Token,authentication,security,api
Author: Walid BENBIHI
Author-email: contact@ocarinow.com
Requires-Python: >=3.9
Classifier: License :: OSI Approved :: MIT License
Classifier: Programming Language :: Python :: 3
Classifier: Programming Language :: Python :: 3.9
Classifier: Programming Language :: Python :: 3.10
Classifier: Programming Language :: Python :: 3.11
Classifier: Programming Language :: Python :: 3.12
Requires-Dist: pydantic (>=1.10)
Requires-Dist: pydantic-settings (>=2.2.1,<3.0.0)
Requires-Dist: pyjwt[crypto] (>=2.8.0,<3.0.0)
Requires-Dist: typing-extensions (>=4.9.0,<5.0.0)
Project-URL: Repository, https://github.com/ocarinow/fastjwt
